qlib/__init__.py
qlib/quantum_objects.py
qlib/hamiltonians/__init__.py
qlib/hamiltonians/dicke_model.py
qlib/hamiltonians/jaynes_cummings.py
qlib/hamiltonians/rabi_model.py
qlib/hamiltonians/tavis_cummings_model.py
qlib/operators/__init__.py
qlib/operators/angular_momentum.py
qlib/operators/creation_annihiliation.py
qlib/operators/pauli_matrices.py
qlib/operators/standard_operators.py
qlib/operators/time_evolution_old_code.py
qlib/operators/time_evolution_scipy.py
qlib/operators/time_evolution_wolfram.py
qlib/solvers/__init__.py
qlib/solvers/eigen.py
qlib/states/__init__.py
qlib/states/quantum_state.py
qlib/states/spin_state.py
qlib/utils/__init__.py
qlib/utils/density_matrix.py
qlib/utils/math_utils.py
qlib/utils/wigner_compute.py
qlib/visualization/__init__.py
qlib/visualization/energy_schema.py
qlib/visualization/expectation_plots.py
qlib/visualization/wigner_plot.py
qdynpylib-0.1.0.dist-info/LICENSE
qdynpylib-0.1.0.dist-info/METADATA
qdynpylib-0.1.0.dist-info/WHEEL
qdynpylib-0.1.0.dist-info/top_level.txt
qdynpylib-0.1.0.dist-info/RECORD
